entangle/__init__.py
entangle-0.0.0.dist-info/LICENSE
entangle-0.0.0.dist-info/METADATA
entangle-0.0.0.dist-info/WHEEL
entangle-0.0.0.dist-info/top_level.txt
entangle-0.0.0.dist-info/RECORD
