Metadata-Version: 2.1
Name: entangle
Version: 0.0.0
Summary: Check and get file hashes (using any algorithm)
Home-page: https://github.com/pypa/sampleproject
Author: social-learning
Author-email: ben.yan.fan@gmail.com
License: UNKNOWN
Platform: UNKNOWN
Classifier: Programming Language :: Python :: 3
Classifier: License :: OSI Approved :: MIT License
Classifier: Operating System :: OS Independent
Requires-Python: >=3.8.5
